{
 "images": [
  {
   "file": "/home/iluvatar/Desktop/ymy/new/video2pic/20pic/ori_pic/14.jpg",
   "max_detection_conf": 0.999,
   "detections": [
    {
     "category": "1",
     "conf": 0.999,
     "bbox": [
      0.3052,
      0.2078,
      0.5128,
      0.3356
     ]
    },
    {
     "category": "1",
     "conf": 0.994,
     "bbox": [
      0.2004,
      0.6429,
      0.3119,
      0.09184
     ]
    },
    {
     "category": "1",
     "conf": 0.0759,
     "bbox": [
      0.7527,
      0.7802,
      0.2472,
      0.09269
     ]
    }
   ]
  }
 ],
 "detection_categories": {
  "1": "animal",
  "2": "person",
  "3": "vehicle"
 },
 "info": {
  "detection_completion_time": "2022-09-23 09:22:00",
  "format_version": "1.2",
  "detector": "md_v4.1.0.pb",
  "detector_metadata": {
   "megadetector_version": "v4.1.0",
   "typical_detection_threshold": 0.8,
   "conservative_detection_threshold": 0.6
  }
 }
}